rescalehtc/__init__.py
rescalehtc/api.py
rescalehtc/bearer_token.py
rescalehtc/container_registry.py
rescalehtc/exceptions.py
rescalehtc/htcjobs.py
rescalehtc/htcprojects.py
rescalehtc/htcsession.py
rescalehtc/htctasks.py
rescalehtc/logger.py
rescalehtc/internals/__init__.py
rescalehtc/internals/authenticate.py
rescalehtc/internals/constants.py
rescalehtc/internals/rest_helpers.py
rescalehtc/scripts/rauthenticate.py
rescalehtc-1.1.0.dist-info/LICENSE
rescalehtc-1.1.0.dist-info/METADATA
rescalehtc-1.1.0.dist-info/WHEEL
rescalehtc-1.1.0.dist-info/entry_points.txt
rescalehtc-1.1.0.dist-info/top_level.txt
rescalehtc-1.1.0.dist-info/RECORD
