Metadata-Version: 2.1
Name: rescalehtc
Version: 1.1.0
Summary: Rescale Control Helpers Package
Author-email: Christian Grovdal <christian.grovdal@arm.com>, Eivind Holsen <eivind.holsen@arm.com>, Bartosz Dobrzelecki <bdobrzelecki@rescale.com>
Project-URL: Homepage, https://rescale.com/platform/hpc-as-a-service/high-throughput-computing/
Project-URL: Documentation, https://rescale-htc-python.readthedocs.io/
Project-URL: Bug Tracker, https://github.com/rescale-labs/rescale-htc-python/issues
Classifier: Programming Language :: Python :: 3
Classifier: License :: OSI Approved :: MIT License
Classifier: Operating System :: OS Independent
Requires-Python: >=3.7
License-File: LICENSE
Requires-Dist: requests >=2
Provides-Extra: dev
Requires-Dist: black ; extra == 'dev'
Requires-Dist: mock ; extra == 'dev'
Requires-Dist: flask ; extra == 'dev'
Requires-Dist: sphinx ; extra == 'dev'
Requires-Dist: sphinx-pyproject ; extra == 'dev'
Requires-Dist: sphinx-rtd-theme ; extra == 'dev'
Requires-Dist: selenium ; extra == 'dev'
Requires-Dist: beautifulsoup4 ; extra == 'dev'
Requires-Dist: Pygments ; extra == 'dev'
